manga_dl/__init__.py
manga_dl/__main__.py
manga_dl/__version__.py
manga_dl/api.py
manga_dl/config.py
manga_dl/exceptions.py
manga_dl/manga.py
manga_dl/pick.py
manga_dl/source.py
manga_dl/utils.py
manga_dl/addons/__init__.py
manga_dl/addons/dogemanga.py
manga_dl/addons/mangabz.py
manga_dl/addons/manhuabei.py
manga_dl/addons/manhuadb.py
manga_dl/addons/manhuagui.py
manga_dl/addons/ykmh.py
test/__init__.py
test/test_addon_mangabz.py
test/test_addon_manhuabei.py
test/test_addon_manhuadb.py
test/test_source.py
pymanga_dl-0.1.12.dist-info/LICENSE
pymanga_dl-0.1.12.dist-info/METADATA
pymanga_dl-0.1.12.dist-info/WHEEL
pymanga_dl-0.1.12.dist-info/entry_points.txt
pymanga_dl-0.1.12.dist-info/top_level.txt
pymanga_dl-0.1.12.dist-info/RECORD
