Metadata-Version: 2.1
Name: pymanga-dl
Version: 0.1.12
Summary: Search and download comic.
Home-page: https://github.com/iworldtong/manga-dl
Author: muketong
Author-email: iworldtong@gmail.com
License: MIT License
Platform: UNKNOWN
Classifier: Development Status :: 2 - Pre-Alpha
Classifier: Environment :: Console
Classifier: Intended Audience :: Developers
Classifier: Intended Audience :: End Users/Desktop
Classifier: License :: OSI Approved :: MIT License
Classifier: Operating System :: OS Independent
Classifier: Programming Language :: Python
Classifier: Programming Language :: Python :: 3
Classifier: Programming Language :: Python :: 3 :: Only
Classifier: Programming Language :: Python :: 3.5
Classifier: Programming Language :: Python :: 3.6
Classifier: Programming Language :: Python :: 3.7
Classifier: Topic :: Internet
Classifier: Topic :: Internet :: WWW/HTTP
Classifier: Topic :: Utilities
Requires-Dist: requests
Requires-Dist: click
Requires-Dist: pycryptodome
Requires-Dist: prettytable
Requires-Dist: tenacity
Requires-Dist: pyaes
Requires-Dist: watchdog
Requires-Dist: PyExecJS
